whatsonpypi/__init__.py
whatsonpypi/__main__.py
whatsonpypi/_version.py
whatsonpypi/cli.py
whatsonpypi/client.py
whatsonpypi/constants.py
whatsonpypi/exceptions.py
whatsonpypi/utils.py
whatsonpypi/whatsonpypi.py
whatsonpypi-0.4.3.dist-info/METADATA
whatsonpypi-0.4.3.dist-info/WHEEL
whatsonpypi-0.4.3.dist-info/entry_points.txt
whatsonpypi-0.4.3.dist-info/licenses/LICENSE
whatsonpypi-0.4.3.dist-info/RECORD
