Metadata-Version: 2.4
Name: whatsonpypi
Version: 0.4.3
Summary: Get package info from PyPI.
Project-URL: Homepage, https://github.com/viseshrp/whatsonpypi
Project-URL: Repository, https://github.com/viseshrp/whatsonpypi
Project-URL: Documentation, https://github.com/viseshrp/whatsonpypi/blob/main/README.md
Project-URL: Changelog, https://github.com/viseshrp/whatsonpypi/blob/main/CHANGELOG.md
Project-URL: Bug-Tracker, https://github.com/viseshrp/whatsonpypi/issues
Project-URL: CI, https://github.com/viseshrp/whatsonpypi/actions
Author-email: Visesh Prasad <viseshrprasad@gmail.com>
License: MIT
License-File: LICENSE
Keywords: pypi,python,requirements,venv,virtualenv,whatsonpypi,wopp
Classifier: Development Status :: 4 - Beta
Classifier: Environment :: Console
Classifier: Intended Audience :: Developers
Classifier: License :: OSI Approved :: MIT License
Classifier: Natural Language :: English
Classifier: Operating System :: OS Independent
Classifier: Programming Language :: Python
Classifier: Programming Language :: Python :: 3
Classifier: Programming Language :: Python :: 3.9
Classifier: Programming Language :: Python :: 3.10
Classifier: Programming Language :: Python :: 3.11
Classifier: Programming Language :: Python :: 3.12
Classifier: Programming Language :: Python :: 3.13
Classifier: Topic :: Software Development :: Libraries :: Python Modules
Requires-Python: <4.0,>=3.9
Requires-Dist: click>=8.1.8
Requires-Dist: requests>=2.32.4
Provides-Extra: rich
Requires-Dist: rich>=13.0.0; extra == 'rich'
